pywinexe/api.py
pywinexe/exceptions.py
pywinexe/models.py
pywinexe/parser.py
pywinexe/__init__.py
pywinexe-1.0.2.dist-info/DESCRIPTION.rst
pywinexe-1.0.2.dist-info/METADATA
pywinexe-1.0.2.dist-info/metadata.json
pywinexe-1.0.2.dist-info/RECORD
pywinexe-1.0.2.dist-info/top_level.txt
pywinexe-1.0.2.dist-info/WHEEL
