Metadata-Version: 2.0
Name: pywinexe
Version: 1.0.2
Summary: A Python wrapper client for the winexe utility
Home-page: https://github.com/tonybaloney/pywinexe
Author: Anthony Shaw
Author-email: anthony.shaw@dimensiondata.com
License: APACHE2
Download-URL: https://github.com/tonybaloney/pywinexe/tarball/1.0.2
Platform: UNKNOWN
Classifier: Development Status :: 3 - Alpha
Classifier: Intended Audience :: Developers
Classifier: Programming Language :: Python :: 3
Classifier: Programming Language :: Python :: 2
